_casc.cp311-win_amd64.pyd
casc.py
casc-0.0.1.dist-info/METADATA
casc-0.0.1.dist-info/WHEEL
casc-0.0.1.dist-info/top_level.txt
casc-0.0.1.dist-info/RECORD
