Metadata-Version: 2.1
Name: casc
Version: 0.0.1
Summary: Python library that binds to CascLib used by Blizzards games
Home-page: https://github.com/Meithal/pycasc
